[
  {"version":2},
  {"ingredient":{"id":"oritech:destroyer_block"},"type":"item_stack","bookmarkType":"INGREDIENT"},
  {"ingredient":{"id":"oritech:pump_block"},"type":"item_stack","bookmarkType":"INGREDIENT"},
  {"ingredient":{"id":"oritech:fuel_generator_block"},"type":"item_stack","bookmarkType":"INGREDIENT"},
  {"ingredient":{"id":"oritech:machine_frame_block"},"type":"item_stack","bookmarkType":"INGREDIENT"},
  {"ingredient":{"id":"oritech:quarry_addon"},"type":"item_stack","bookmarkType":"INGREDIENT"},
  {"ingredient":{"id":"oritech:machine_efficiency_addon"},"type":"item_stack","bookmarkType":"INGREDIENT"},
  {"ingredient":{"id":"oritech:machine_speed_addon"},"type":"item_stack","bookmarkType":"INGREDIENT"},
  {"ingredient":{"id":"oritech:small_storage_block"},"type":"item_stack","bookmarkType":"INGREDIENT"},
  {"ingredient":{"id":"oritech:transparent_item_pipe"},"type":"item_stack","bookmarkType":"INGREDIENT"},
  {"ingredient":{"id":"minecraft:spruce_fence_gate"},"type":"item_stack","bookmarkType":"INGREDIENT"},
  {"ingredient":{"id":"oritech:basic_generator_block"},"type":"item_stack","bookmarkType":"INGREDIENT"},
  {"ingredient":{"id":"oritech:motor"},"type":"item_stack","bookmarkType":"INGREDIENT"},
  {"ingredient":{"id":"minecraft:ender_pearl"},"type":"item_stack","bookmarkType":"INGREDIENT"},
  {"ingredient":{"id":"oritech:fluxite"},"type":"item_stack","bookmarkType":"INGREDIENT"},
  {"ingredient":{"id":"oritech:advanced_battery"},"type":"item_stack","bookmarkType":"INGREDIENT"},
  {"ingredient":{"id":"oritech:flux_gate"},"type":"item_stack","bookmarkType":"INGREDIENT"},
  {"ingredient":{"id":"oritech:processing_unit"},"type":"item_stack","bookmarkType":"INGREDIENT"}
]